README.rst
setup.py
yaml_backed_structs/__init__.py
yaml_backed_structs/persistent_dict.py
yaml_backed_structs/persistent_set.py
yaml_backed_structs.egg-info/PKG-INFO
yaml_backed_structs.egg-info/SOURCES.txt
yaml_backed_structs.egg-info/dependency_links.txt
yaml_backed_structs.egg-info/requires.txt
yaml_backed_structs.egg-info/top_level.txt