Metadata-Version: 1.1
Name: yaml-backed-structs
Version: 0.9.0
Summary: Basic python data structures backed by a human editable yaml file
Home-page: https://github.com/dcdanko/YamlBackedPyStructs
Author: David C. Danko
Author-email: dcdanko@gmail.com
License: UNKNOWN
Platform: UNKNOWN
Classifier: Development Status :: 4 - Beta
Classifier: Programming Language :: Python :: 3
Classifier: Programming Language :: Python :: 3.4
Classifier: Programming Language :: Python :: 3.5
